synapse/__init__.py
synapse/event_auth.py
synapse/notifier.py
synapse/py.typed
synapse/server.py
synapse/synapse_rust.abi3.so
synapse/visibility.py
synapse/_scripts/__init__.py
synapse/_scripts/export_signing_key.py
synapse/_scripts/generate_config.py
synapse/_scripts/generate_log_config.py
synapse/_scripts/generate_signing_key.py
synapse/_scripts/generate_workers_map.py
synapse/_scripts/hash_password.py
synapse/_scripts/move_remote_media_to_new_store.py
synapse/_scripts/register_new_matrix_user.py
synapse/_scripts/review_recent_signups.py
synapse/_scripts/synapse_port_db.py
synapse/_scripts/synctl.py
synapse/_scripts/update_synapse_database.py
synapse/api/__init__.py
synapse/api/auth_blocking.py
synapse/api/constants.py
synapse/api/errors.py
synapse/api/filtering.py
synapse/api/presence.py
synapse/api/ratelimiting.py
synapse/api/room_versions.py
synapse/api/urls.py
synapse/api/auth/__init__.py
synapse/api/auth/base.py
synapse/api/auth/internal.py
synapse/api/auth/mas.py
synapse/api/auth/msc3861_delegated.py
synapse/app/__init__.py
synapse/app/_base.py
synapse/app/admin_cmd.py
synapse/app/appservice.py
synapse/app/client_reader.py
synapse/app/complement_fork_starter.py
synapse/app/event_creator.py
synapse/app/federation_reader.py
synapse/app/federation_sender.py
synapse/app/frontend_proxy.py
synapse/app/generic_worker.py
synapse/app/homeserver.py
synapse/app/media_repository.py
synapse/app/phone_stats_home.py
synapse/app/pusher.py
synapse/app/synchrotron.py
synapse/app/user_dir.py
synapse/appservice/__init__.py
synapse/appservice/api.py
synapse/appservice/scheduler.py
synapse/config/__init__.py
synapse/config/__main__.py
synapse/config/_base.py
synapse/config/_base.pyi
synapse/config/_util.py
synapse/config/account_validity.py
synapse/config/api.py
synapse/config/appservice.py
synapse/config/auth.py
synapse/config/auto_accept_invites.py
synapse/config/background_updates.py
synapse/config/cache.py
matrix_synapse-1.142.0.dist-info/AUTHORS.rst
matrix_synapse-1.142.0.dist-info/LICENSE-AGPL-3.0
matrix_synapse-1.142.0.dist-info/LICENSE-COMMERCIAL
matrix_synapse-1.142.0.dist-info/METADATA
matrix_synapse-1.142.0.dist-info/WHEEL
matrix_synapse-1.142.0.dist-info/entry_points.txt
matrix_synapse-1.142.0.dist-info/RECORD
