Metadata-Version: 2.3
Name: matrix-synapse
Version: 1.142.0
Summary: Homeserver for the Matrix decentralised comms protocol
License: AGPL-3.0-or-later OR LicenseRef-Element-Commercial
Author: Matrix.org Team and Contributors
Author-email: packages@matrix.org
Requires-Python: >=3.10.0,<4.0.0
Classifier: Development Status :: 5 - Production/Stable
Classifier: License :: Other/Proprietary License
Classifier: Programming Language :: Python :: 3
Classifier: Programming Language :: Python :: 3.10
Classifier: Programming Language :: Python :: 3.11
Classifier: Programming Language :: Python :: 3.12
Classifier: Programming Language :: Python :: 3.13
Classifier: Topic :: Communications :: Chat
Provides-Extra: all
Provides-Extra: cache-memory
Provides-Extra: jwt
Provides-Extra: matrix-synapse-ldap3
Provides-Extra: oidc
Provides-Extra: opentracing
Provides-Extra: postgres
Provides-Extra: redis
Provides-Extra: saml2
Provides-Extra: sentry
Provides-Extra: systemd
Provides-Extra: test
Provides-Extra: url-preview
Requires-Dist: Jinja2 (>=3.0)
Requires-Dist: Pillow (>=10.0.1)
Requires-Dist: PyYAML (>=5.3)
Requires-Dist: Pympler ; extra == "cache-memory" or extra == "all"
Requires-Dist: Twisted[tls] (>=21.2.0)
Requires-Dist: attrs (>=19.2.0,!=21.1.0)
Requires-Dist: authlib (>=0.15.1) ; extra == "oidc" or extra == "jwt" or extra == "all"
Requires-Dist: bcrypt (>=3.1.7)
Requires-Dist: bleach (>=3.2.0)
Requires-Dist: canonicaljson (>=2.0.0,<3.0.0)
Requires-Dist: cryptography (>=3.4.7)
Requires-Dist: hiredis ; extra == "redis" or extra == "all"
Requires-Dist: idna (>=2.5) ; extra == "test"
Requires-Dist: ijson (>=3.1.4)
Requires-Dist: immutabledict (>=2.0)
Requires-Dist: jaeger-client (>=4.2.0) ; extra == "opentracing" or extra == "all"
Requires-Dist: jsonschema (>=3.0.0)
Requires-Dist: lxml (>=4.6.3) ; extra == "url-preview" or extra == "all"
Requires-Dist: matrix-common (>=1.3.0,<2.0.0)
Requires-Dist: matrix-synapse-ldap3 (>=0.1) ; extra == "matrix-synapse-ldap3" or extra == "all"
Requires-Dist: msgpack (>=0.5.2)
Requires-Dist: netaddr (>=0.7.18)
Requires-Dist: opentracing (>=2.2.0) ; extra == "opentracing" or extra == "all"
Requires-Dist: packaging (>=20.0)
Requires-Dist: parameterized (>=0.7.4) ; extra == "test"
Requires-Dist: phonenumbers (>=8.2.0)
Requires-Dist: prometheus-client (>=0.6.0)
Requires-Dist: psycopg2 (>=2.8) ; (platform_python_implementation != "PyPy") and (extra == "postgres" or extra == "all")
Requires-Dist: psycopg2cffi (>=2.8) ; (platform_python_implementation == "PyPy") and (extra == "postgres" or extra == "all")
Requires-Dist: psycopg2cffi-compat (==1.1) ; (platform_python_implementation == "PyPy") and (extra == "postgres" or extra == "all")
Requires-Dist: pyOpenSSL (>=16.0.0)
Requires-Dist: pyasn1 (>=0.1.9)
Requires-Dist: pyasn1-modules (>=0.0.7)
Requires-Dist: pydantic (>=2.12,<3.0) ; python_version >= "3.14"
Requires-Dist: pydantic (>=2.8,<3.0) ; python_version < "3.14"
Requires-Dist: pymacaroons (>=0.13.0)
Requires-Dist: pysaml2 (>=4.5.0) ; extra == "saml2" or extra == "all"
Requires-Dist: python-multipart (>=0.0.9)
Requires-Dist: rpds-py (>=0.25.0)
Requires-Dist: sentry-sdk (>=0.7.2) ; extra == "sentry" or extra == "all"
Requires-Dist: service-identity (>=18.1.0)
Requires-Dist: setuptools_rust (>=1.3)
Requires-Dist: signedjson (>=1.1.0,<2.0.0)
Requires-Dist: sortedcontainers (>=2.0.5)
Requires-Dist: systemd-python (>=231) ; extra == "systemd"
Requires-Dist: treq (>=21.5.0)
Requires-Dist: txredisapi (>=1.4.7) ; extra == "redis" or extra == "all"
Requires-Dist: typing-extensions (>=4.14.1)
Requires-Dist: unpaddedbase64 (>=2.1.0)
Project-URL: Repository, https://github.com/element-hq/synapse
